{
  "_schemaVersion": 6,
  "_lastMCVersionId": 763,
  "generalSettings": {
    "detectATLauncherInstance": false,
    "detectCurseManifest": true,
    "detectMultiMCManifest": false,
    "detectMCUpdaterInstance": false,
    "detectTechnicPack": true,
    "detectModrinthPack": true,
    "detectBiomeData": true,
    "detectDimensionData": true,
    "detectWorldData": true,
    "clientId": "1189960133225230607",
    "defaultIcon": "bh_logo",
    "enableJoinRequests": false,
    "preferredClientLevel": 3,
    "resetTimeOnInit": false,
    "autoRegister": false
  },
  "biomeSettings": {
    "fallbackBiomeIcon": "bh_logo",
    "biomeData": {
      "default": {
        "textOverride": "Playing in {biome.name}"
      }
    }
  },
  "dimensionSettings": {
    "fallbackDimensionIcon": "bh_logo",
    "dimensionData": {
      "default": {
        "textOverride": "In the {dimension.name}"
      }
    }
  },
  "serverSettings": {
    "fallbackServerIcon": "bh_logo",
    "fallbackServerName": "Elementblend Server",
    "fallbackServerMotd": "Elementblend Modpack Server",
    "serverData": {
      "default": {
        "textOverride": "Playing on Elementblend Modpack Server"
      }
    }
  },
  "statusMessages": {
    "mainMenuData": {
      "textOverride": "In the Main Menu"
    },
    "loadingData": {
      "textOverride": "Loading..."
    },
    "lanData": {
      "textOverride": "Playing on a LAN Server"
    },
    "singleplayerData": {
      "textOverride": "Playing Singleplayer",
      "data": {
        "enabled": true,
        "useAsMain": false,
        "isInstance": false,
        "activityType": 0,
        "partyPrivacy": 1,
        "details": "",
        "gameState": "",
        "largeImageKey": "",
        "largeImageText": "",
        "smallImageKey": "",
        "smallImageText": "",
        "startTimestamp": "",
        "endTimestamp": "",
        "buttons": {
          "default": {
            "label": "Example Text",
            "url": "https://google.com"
          }
        }
      }
    },
    "realmData": {
      "textOverride": "Playing on {server.motd.raw}"
    }
  },
  "advancedSettings": {
    "enablePerGui": false,
    "enablePerItem": false,
    "enablePerEntity": false,
    "formatWords": true,
    "debugMode": false,
    "verboseMode": false,
    "refreshRate": 2,
    "allowPlaceholderPreviews": false,
    "guiSettings": {
      "fallbackGuiIcon": "unknown",
      "guiData": {
        "default": {
          "textOverride": "In {screen.name}"
        }
      }
    },
    "itemMessages": {
      "default": "Holding {item.message.holding}"
    },
    "entitySettings": {
      "fallbackEntityIcon": "unknown",
      "targetData": {
        "default": {
          "textOverride": "Targeting {entity.target.name}"
        }
      },
      "ridingData": {
        "default": {
          "textOverride": "Riding {entity.riding.name}"
        }
      }
    },
    "allowEndpointIcons": true,
    "serverIconEndpoint": "https://api.mcsrvstat.us/icon/{server.address.short}",
    "playerSkinEndpoint": "https://mc-heads.net/avatar/{getOrDefault(player.uuid.short, player.name)}",
    "allowDuplicatePackets": false,
    "maxConnectionAttempts": 10,
    "enableClassGraph": false
  },
  "accessibilitySettings": {
    "languageId": "en_us",
    "stripTranslationColors": false,
    "stripTranslationFormatting": false,
    "stripExtraGuiElements": false,
    "configKeyCode": -1
  },
  "displaySettings": {
    "presenceData": {
      "enabled": true,
      "useAsMain": false,
      "isInstance": false,
      "activityType": 0,
      "partyPrivacy": 1,
      "details": "{getFirst(menu.message, dimension.message)}",
      "gameState": "{getOrDefault(server.message)} {getOrDefault(pack.name)}",
      "largeImageKey": "{getFirst(menu.icon, dimension.icon)}",
      "largeImageText": "{getFirst(menu.message, dimension.message)}",
      "smallImageKey": "{getFirst(server.icon, pack.icon)}",
      "smallImageText": "{getOrDefault(server.message)} {getOrDefault(pack.name)}",
      "startTimestamp": "{data.general.time}",
      "endTimestamp": "",
      "buttons": {
        "default": {
          "label": "Example Text",
          "url": "https://google.com"
        }
      }
    },
    "dynamicIcons": {
      "default": "https://via.placeholder.com/256.png",
      "localhost": "https://api.mcsrvstat.us/icon/localhost",
      "SamLam140330": "https://mc-heads.net/avatar/3ca3e1330b0e4ffcb405da74a3e2f985",
      "mod.elementblend.com": "https://api.mcsrvstat.us/icon/mod.elementblend.com"
    },
    "dynamicVariables": {
      "default": "Example Text",
      "mods": "{general.mods} Mod(s)",
      "player_info_coordinate": "At {player.position.x}, {player.position.z}",
      "players": "{server.players.current} / {server.players.max} Players",
      "player_info_in": "({custom.player_info.health})",
      "player_info_items": "Items: {item.main_hand.message}",
      "player_info_out": "As {player.name}",
      "player_info_health": "Health: {player.health.current}/{player.health.max}",
      "world_info": "On {world.name}",
      "pack": "{pack.name}"
    }
  }
}